glide_sdk_python/__init__.py
glide_sdk_python/client.py
glide_sdk_python/logger.py
glide_sdk_python/session.py
glide_sdk_python/utils.py
glide_sdk_python-0.1.0.dist-info/METADATA
glide_sdk_python-0.1.0.dist-info/WHEEL
glide_sdk_python-0.1.0.dist-info/RECORD
